.project
setup.py
suxdigest.py
suxssh.py
sync.py
src/suxsync/__init__.py
src/suxsync/config.py
src/suxsync/digest.py
src/suxsync/download.py
src/suxsync/ssh_session.py
src/suxsync/sync.py
src/suxsync/util.py
src/suxsync.egg-info/PKG-INFO
src/suxsync.egg-info/SOURCES.txt
src/suxsync.egg-info/dependency_links.txt
src/suxsync.egg-info/top_level.txt
src/suxsync.egg-info/zip-safe