Metadata-Version: 1.0
Name: suxsync
Version: 0.2.4
Summary: A very sucky replacement for Rsync for people with sucky ISPs.
Home-page: http://code.google.com/p/suxtools/
Author: Salim Fadhley
Author-email: sal@stodge.org
License: GPL
Keywords: rsync isp suck
Platform: UNKNOWN
